classifier/__init__.py
classifier/cnn_classifier.py
privacygan/__init__.py
privacygan/privacy_gan.py
privacygan/cifar/__init__.py
privacygan/cifar/cifar_gan.py
privacygan/lfw/__init__.py
privacygan/lfw/lfw_gan.py
privacygan/mnist/__init__.py
privacygan/mnist/mnist_gan.py
privGan-1.0.dist-info/LICENSE
privGan-1.0.dist-info/METADATA
privGan-1.0.dist-info/WHEEL
privGan-1.0.dist-info/top_level.txt
privGan-1.0.dist-info/RECORD
